LICENSE
README.md
setup.py
weather_app/main.py
weather_app/utils.py
weather_app_mehdirazajaffri.egg-info/PKG-INFO
weather_app_mehdirazajaffri.egg-info/SOURCES.txt
weather_app_mehdirazajaffri.egg-info/dependency_links.txt
weather_app_mehdirazajaffri.egg-info/entry_points.txt
weather_app_mehdirazajaffri.egg-info/requires.txt
weather_app_mehdirazajaffri.egg-info/top_level.txt